setup.py
mete/__init__.py
mete/beta_lookup_table.pck
mete/beta_lookuptable_builder.py
mete/mete.py
mete/tests_mete.py
mete.egg-info/PKG-INFO
mete.egg-info/SOURCES.txt
mete.egg-info/dependency_links.txt
mete.egg-info/top_level.txt
mete_distributions/__init__.py
mete_distributions/mete_distributions.py