Metadata-Version: 1.0
Name: mete
Version: 0.1
Summary: Tools for analying the Maximum Entropy Theory of Ecology
Home-page: https://github.com/weecology/mete
Author: Ethan White, Dan McGlinn, Xiao Xiao, Sarah Supp, and Katherine Thibault
Author-email: UNKNOWN
License: MIT
Platform: UNKNOWN
